content_size_limit_asgi/__init__.py
content_size_limit_asgi/errors.py
content_size_limit_asgi/logger.py
content_size_limit_asgi/middleware.py
content_size_limit_asgi-0.1.5.dist-info/WHEEL
content_size_limit_asgi-0.1.5.dist-info/METADATA
content_size_limit_asgi-0.1.5.dist-info/RECORD
