Metadata-Version: 2.1
Name: content-size-limit-asgi
Version: 0.1.5
Summary: An ASGI3 middleware to implement maximum content size limits (mostly useful for HTTP uploads)
License: MIT
Author: Steinn Eldjárn Sigurðarson
Author-email: steinnes@gmail.com
Requires-Python: >=3.6,<4.0
Classifier: License :: OSI Approved :: MIT License
Classifier: Programming Language :: Python :: 3
Classifier: Programming Language :: Python :: 3.6
Classifier: Programming Language :: Python :: 3.7
Classifier: Programming Language :: Python :: 3.8
Classifier: Programming Language :: Python :: 3.9
